[
  {
    "file": "invoice_3914339902472_r1842014.pdf",
    "invoice_number": "3914339902472",
    "invoice_date": "2025-11-01",
    "period_raw": "08 oktober 2025 t/m 24 oktober 2025",
    "period_from": "2025-10-08",
    "period_to": "2025-10-24",
    "type": "settlement",
    "commission": 4.32,
    "sales_revenue": 27.99,
    "net_receivable": 23.67,
    "advertising_cost": 0.0
  },
  {
    "file": "invoice_3914430288168_r1842014.pdf",
    "invoice_number": "3914430288168",
    "invoice_date": "2025-11-15",
    "period_raw": "25 oktober 2025 t/m 07 november 2025",
    "period_from": "2025-10-25",
    "period_to": "2025-11-07",
    "type": "settlement",
    "commission": 8.64,
    "sales_revenue": 55.98,
    "net_receivable": 47.34,
    "advertising_cost": 0.0
  },
  {
    "file": "invoice_3914430288565_r1842014.pdf",
    "invoice_number": "3914430288565",
    "invoice_date": "2025-11-15",
    "period_raw": "25 oktober 2025 t/m 07 november 2025",
    "period_from": "2025-10-25",
    "period_to": "2025-11-07",
    "type": "advertising",
    "advertising_cost": 32.99,
    "net_receivable": -32.99,
    "commission": 0.0,
    "sales_revenue": 0.0
  },
  {
    "file": "invoice_3914573350533_r1842014.pdf",
    "invoice_number": "3914573350533",
    "invoice_date": "2025-12-01",
    "period_raw": "08 november 2025 t/m 23 november 2025",
    "period_from": "2025-11-08",
    "period_to": "2025-11-23",
    "type": "settlement",
    "commission": 21.6,
    "sales_revenue": 139.95,
    "net_receivable": 118.35,
    "advertising_cost": 0.0
  },
  {
    "file": "invoice_3914573350555_r1842014.pdf",
    "invoice_number": "3914573350555",
    "invoice_date": "2025-12-01",
    "period_raw": "08 november 2025 t/m 23 november 2025",
    "period_from": "2025-11-08",
    "period_to": "2025-11-23",
    "type": "advertising",
    "advertising_cost": 10.72,
    "net_receivable": -10.72,
    "commission": 0.0,
    "sales_revenue": 0.0
  },
  {
    "file": "invoice_3914706288287_r1842014.pdf",
    "invoice_number": "3914706288287",
    "invoice_date": "2025-12-15",
    "period_raw": "24 november 2025 t/m 07 december 2025",
    "period_from": "2025-11-24",
    "period_to": "2025-12-07",
    "type": "settlement",
    "commission": 6.7,
    "sales_revenue": 43.98,
    "net_receivable": 37.28,
    "advertising_cost": 0.0
  },
  {
    "file": "invoice_3914706611429_r1842014.pdf",
    "invoice_number": "3914706611429",
    "invoice_date": "2025-12-15",
    "period_raw": "24 november 2025 t/m 07 december 2025",
    "period_from": "2025-11-24",
    "period_to": "2025-12-07",
    "type": "advertising",
    "advertising_cost": 14.88,
    "net_receivable": -14.88,
    "commission": 0.0,
    "sales_revenue": 0.0
  },
  {
    "file": "invoice_3914837396077_r1842014.pdf",
    "invoice_number": "3914837396077",
    "invoice_date": "2026-01-01",
    "period_raw": "08 december 2025 t/m 24 december 2025",
    "period_from": "2025-12-08",
    "period_to": "2025-12-24",
    "type": "settlement",
    "commission": 52.88,
    "sales_revenue": 331.8,
    "net_receivable": 278.92,
    "advertising_cost": 0.0
  },
  {
    "file": "invoice_3914837397863_r1842014.pdf",
    "invoice_number": "3914837397863",
    "invoice_date": "2026-01-01",
    "period_raw": "08 december 2025 t/m 24 december 2025",
    "period_from": "2025-12-08",
    "period_to": "2025-12-24",
    "type": "advertising",
    "advertising_cost": 111.21,
    "net_receivable": -111.21,
    "commission": 0.0,
    "sales_revenue": 0.0
  },
  {
    "file": "invoice_3914925779961_r1842014.pdf",
    "invoice_number": "3914925779961",
    "invoice_date": "2026-01-15",
    "period_raw": "25 december 2025 t/m 07 januari 2026",
    "period_from": "2025-12-25",
    "period_to": "2026-01-07",
    "type": "advertising",
    "advertising_cost": 16.93,
    "net_receivable": -16.93,
    "commission": 0.0,
    "sales_revenue": 0.0
  },
  {
    "file": "invoice_3914925779983_r1842014.pdf",
    "invoice_number": "3914925779983",
    "invoice_date": "2026-01-15",
    "period_raw": "25 december 2025 t/m 07 januari 2026",
    "period_from": "2025-12-25",
    "period_to": "2026-01-07",
    "type": "settlement",
    "commission": 19.66,
    "sales_revenue": 127.95,
    "net_receivable": 108.29,
    "advertising_cost": 0.0
  },
  {
    "file": "invoice_3915026906182_r1842014.pdf",
    "invoice_number": "3915026906182",
    "invoice_date": "2026-02-01",
    "period_raw": "08 januari 2026 t/m 24 januari 2026",
    "period_from": "2026-01-08",
    "period_to": "2026-01-24",
    "type": "settlement",
    "commission": 38.2,
    "sales_revenue": 223.92,
    "net_receivable": 185.72,
    "advertising_cost": 0.0
  },
  {
    "file": "invoice_3915027084781_r1842014.pdf",
    "invoice_number": "3915027084781",
    "invoice_date": "2026-02-01",
    "period_raw": "08 januari 2026 t/m 24 januari 2026",
    "period_from": "2026-01-08",
    "period_to": "2026-01-24",
    "type": "advertising",
    "advertising_cost": 28.44,
    "net_receivable": -28.44,
    "commission": 0.0,
    "sales_revenue": 0.0
  },
  {
    "file": "invoice_3915109228854_r1842014.pdf",
    "invoice_number": "3915109228854",
    "invoice_date": "2026-02-15",
    "period_raw": "25 januari 2026 t/m 07 februari 2026",
    "period_from": "2026-01-25",
    "period_to": "2026-02-07",
    "type": "advertising",
    "advertising_cost": 21.81,
    "net_receivable": -21.81,
    "commission": 0.0,
    "sales_revenue": 0.0
  },
  {
    "file": "invoice_3915109288426_r1842014.pdf",
    "invoice_number": "3915109288426",
    "invoice_date": "2026-02-15",
    "period_raw": "25 januari 2026 t/m 07 februari 2026",
    "period_from": "2026-01-25",
    "period_to": "2026-02-07",
    "type": "settlement",
    "commission": 12.96,
    "sales_revenue": 83.97,
    "net_receivable": 71.01,
    "advertising_cost": 0.0
  },
  {
    "file": "invoice_3915186137844_r1842014.pdf",
    "invoice_number": "3915186137844",
    "invoice_date": "2026-03-01",
    "period_raw": "08 februari 2026 t/m 21 februari 2026",
    "period_from": "2026-02-08",
    "period_to": "2026-02-21",
    "type": "advertising",
    "advertising_cost": 13.08,
    "net_receivable": -13.08,
    "commission": 0.0,
    "sales_revenue": 0.0
  },
  {
    "file": "invoice_3915186156691_r1842014.pdf",
    "invoice_number": "3915186156691",
    "invoice_date": "2026-03-01",
    "period_raw": "08 februari 2026 t/m 21 februari 2026",
    "period_from": "2026-02-08",
    "period_to": "2026-02-21",
    "type": "settlement",
    "commission": 12.96,
    "sales_revenue": 83.97,
    "net_receivable": 71.01,
    "advertising_cost": 0.0
  },
  {
    "file": "invoice_3915264643719_r1842014.pdf",
    "invoice_number": "3915264643719",
    "invoice_date": "2026-03-15",
    "period_raw": "22 februari 2026 t/m 07 maart 2026",
    "period_from": "2026-02-22",
    "period_to": "2026-03-07",
    "type": "settlement",
    "commission": 4.32,
    "sales_revenue": 27.99,
    "net_receivable": 23.67,
    "advertising_cost": 0.0
  },
  {
    "file": "invoice_3915264671408_r1842014.pdf",
    "invoice_number": "3915264671408",
    "invoice_date": "2026-03-15",
    "period_raw": "22 februari 2026 t/m 07 maart 2026",
    "period_from": "2026-02-22",
    "period_to": "2026-03-07",
    "type": "advertising",
    "advertising_cost": 10.7,
    "net_receivable": -10.7,
    "commission": 0.0,
    "sales_revenue": 0.0
  },
  {
    "file": "invoice_3915368670561_r1842014.pdf",
    "invoice_number": "3915368670561",
    "invoice_date": "2026-04-01",
    "period_raw": "08 maart 2026 t/m 24 maart 2026",
    "period_from": "2026-03-08",
    "period_to": "2026-03-24",
    "type": "settlement",
    "commission": 17.28,
    "sales_revenue": 111.96,
    "net_receivable": 94.68,
    "advertising_cost": 0.0
  },
  {
    "file": "invoice_3915368762998_r1842014.pdf",
    "invoice_number": "3915368762998",
    "invoice_date": "2026-04-01",
    "period_raw": "08 maart 2026 t/m 24 maart 2026",
    "period_from": "2026-03-08",
    "period_to": "2026-03-24",
    "type": "advertising",
    "advertising_cost": 12.49,
    "net_receivable": -12.49,
    "commission": 0.0,
    "sales_revenue": 0.0
  },
  {
    "file": "invoice_3915443250020_r1842014.pdf",
    "invoice_number": "3915443250020",
    "invoice_date": "2026-04-15",
    "period_raw": "25 maart 2026 t/m 07 april 2026",
    "period_from": "2026-03-25",
    "period_to": "2026-04-07",
    "type": "settlement",
    "commission": 17.28,
    "sales_revenue": 111.96,
    "net_receivable": 94.68,
    "advertising_cost": 0.0
  },
  {
    "file": "invoice_3915443251522_r1842014.pdf",
    "invoice_number": "3915443251522",
    "invoice_date": "2026-04-15",
    "period_raw": "25 maart 2026 t/m 07 april 2026",
    "period_from": "2026-03-25",
    "period_to": "2026-04-07",
    "type": "advertising",
    "advertising_cost": 12.27,
    "net_receivable": -12.27,
    "commission": 0.0,
    "sales_revenue": 0.0
  },
  {
    "file": "invoice_3915531353817_r1842014.pdf",
    "invoice_number": "3915531353817",
    "invoice_date": "2026-05-01",
    "period_raw": "08 april 2026 t/m 23 april 2026",
    "period_from": "2026-04-08",
    "period_to": "2026-04-23",
    "type": "advertising",
    "advertising_cost": 14.48,
    "net_receivable": -14.48,
    "commission": 0.0,
    "sales_revenue": 0.0
  },
  {
    "file": "invoice_3915531379195_r1842014.pdf",
    "invoice_number": "3915531379195",
    "invoice_date": "2026-05-01",
    "period_raw": "08 april 2026 t/m 23 april 2026",
    "period_from": "2026-04-08",
    "period_to": "2026-04-23",
    "type": "settlement",
    "commission": 17.28,
    "sales_revenue": 111.96,
    "net_receivable": 94.68,
    "advertising_cost": 0.0
  },
  {
    "file": "invoice_3915609037488_r1842014.pdf",
    "invoice_number": "3915609037488",
    "invoice_date": "2026-05-15",
    "period_raw": "24 april 2026 t/m 07 mei 2026",
    "period_from": "2026-04-24",
    "period_to": "2026-05-07",
    "type": "advertising",
    "advertising_cost": 8.33,
    "net_receivable": -8.33,
    "commission": 0.0,
    "sales_revenue": 0.0
  },
  {
    "file": "invoice_3915713184869_r1842014.pdf",
    "invoice_number": "3915713184869",
    "invoice_date": "2026-06-01",
    "period_raw": "08 mei 2026 t/m 24 mei 2026",
    "period_from": "2026-05-08",
    "period_to": "2026-05-24",
    "type": "advertising",
    "advertising_cost": 9.84,
    "net_receivable": -9.84,
    "commission": 0.0,
    "sales_revenue": 0.0
  },
  {
    "file": "invoice_3915713184871_r1842014.pdf",
    "invoice_number": "3915713184871",
    "invoice_date": "2026-06-01",
    "period_raw": "08 mei 2026 t/m 24 mei 2026",
    "period_from": "2026-05-08",
    "period_to": "2026-05-24",
    "type": "settlement",
    "commission": 12.96,
    "sales_revenue": 83.97,
    "net_receivable": 71.01,
    "advertising_cost": 0.0
  },
  {
    "file": "invoice_3915798941361_r1842014.pdf",
    "invoice_number": "3915798941361",
    "invoice_date": "2026-06-15",
    "period_raw": "25 mei 2026 t/m 07 juni 2026",
    "period_from": "2026-05-25",
    "period_to": "2026-06-07",
    "type": "advertising",
    "advertising_cost": 7.85,
    "net_receivable": -7.85,
    "commission": 0.0,
    "sales_revenue": 0.0
  },
  {
    "file": "invoice_3915798951048_r1842014.pdf",
    "invoice_number": "3915798951048",
    "invoice_date": "2026-06-15",
    "period_raw": "25 mei 2026 t/m 07 juni 2026",
    "period_from": "2026-05-25",
    "period_to": "2026-06-07",
    "type": "settlement",
    "commission": 12.96,
    "sales_revenue": 83.97,
    "net_receivable": 71.01,
    "advertising_cost": 0.0
  }
]